agentpack/__init__.py
agentpack/context.py
agentpack/errors.py
agentpack/server.py.deprecated
agentpack/tool.py
agentpack/types.py
agentpack-0.1.0.dist-info/METADATA
agentpack-0.1.0.dist-info/WHEEL
agentpack-0.1.0.dist-info/RECORD
