Metadata-Version: 2.4
Name: agentpack
Version: 0.1.0
Summary: Python SDK for building Agentpack tools
Project-URL: Homepage, https://github.com/northcognitive/agentpack
Project-URL: Documentation, https://github.com/northcognitive/agentpack/tree/main/sdks/python
Project-URL: Repository, https://github.com/northcognitive/agentpack
Author: Agentpack Contributors
License: Apache-2.0
Keywords: agentpack,agents,ai,llm,tools
Classifier: Development Status :: 3 - Alpha
Classifier: Intended Audience :: Developers
Classifier: License :: OSI Approved :: Apache Software License
Classifier: Programming Language :: Python :: 3
Classifier: Programming Language :: Python :: 3.10
Classifier: Programming Language :: Python :: 3.11
Classifier: Programming Language :: Python :: 3.12
Requires-Python: >=3.10
Requires-Dist: fastapi>=0.109.0
Requires-Dist: httpx>=0.26.0
Requires-Dist: opentelemetry-api>=1.22.0
Requires-Dist: opentelemetry-exporter-otlp>=1.22.0
Requires-Dist: opentelemetry-instrumentation-fastapi>=0.43b0
Requires-Dist: opentelemetry-sdk>=1.22.0
Requires-Dist: pydantic>=2.5.0
Requires-Dist: structlog>=24.1.0
Requires-Dist: uvicorn[standard]>=0.27.0
Provides-Extra: dev
Requires-Dist: black>=23.12.0; extra == 'dev'
Requires-Dist: mypy>=1.8.0; extra == 'dev'
Requires-Dist: pytest-asyncio>=0.23.0; extra == 'dev'
Requires-Dist: pytest-cov>=4.1.0; extra == 'dev'
Requires-Dist: pytest>=7.4.0; extra == 'dev'
Requires-Dist: ruff>=0.1.0; extra == 'dev'
